airflow_clickhouse_plugin/hooks/clickhouse.py
airflow_clickhouse_plugin/hooks/clickhouse_dbapi.py
airflow_clickhouse_plugin/operators/clickhouse.py
airflow_clickhouse_plugin/operators/clickhouse_dbapi.py
airflow_clickhouse_plugin/sensors/clickhouse.py
airflow_clickhouse_plugin/sensors/clickhouse_dbapi.py
airflow_clickhouse_plugin-1.5.0.dist-info/licenses/LICENSE
airflow_clickhouse_plugin-1.5.0.dist-info/METADATA
airflow_clickhouse_plugin-1.5.0.dist-info/WHEEL
airflow_clickhouse_plugin-1.5.0.dist-info/top_level.txt
airflow_clickhouse_plugin-1.5.0.dist-info/RECORD
